yaqd_andor/VERSION
yaqd_andor/__init__.py
yaqd_andor/__version__.py
yaqd_andor/_andor_client_example.py
yaqd_andor/_andor_neo.py
yaqd_andor/_andor_sdk3.py
yaqd_andor/_andor_simcam.py
yaqd_andor/_andor_sona.py
yaqd_andor/andor-neo.avpr
yaqd_andor/andor-neo.toml
yaqd_andor/andor-simcam.avpr
yaqd_andor/andor-simcam.toml
yaqd_andor/andor-sona.avpr
yaqd_andor/andor-sona.toml
yaqd_andor/atcore.py
yaqd_andor/features.py
yaqd_andor-2022.6.0.dist-info/entry_points.txt
yaqd_andor-2022.6.0.dist-info/LICENSE
yaqd_andor-2022.6.0.dist-info/WHEEL
yaqd_andor-2022.6.0.dist-info/METADATA
yaqd_andor-2022.6.0.dist-info/RECORD
