Metadata-Version: 2.1
Name: yaqd-andor
Version: 2022.6.0
Summary: Daemons for [Andor](https://andor.oxinst.com) cameras
Home-page: https://yaq.fyi
Author: yaq developers
Requires-Python: >=3.7
Classifier: Development Status :: 2 - Pre-Alpha
Classifier: Intended Audience :: Science/Research
Classifier: License :: OSI Approved :: GNU Lesser General Public License v3 (LGPLv3)
Classifier: Natural Language :: English
Classifier: Programming Language :: Python :: 3
Classifier: Programming Language :: Python :: 3.7
Classifier: Programming Language :: Python :: 3.8
Classifier: Topic :: Scientific/Engineering
Requires-Dist: yaqd-core>=2021.03.0
Requires-Dist: setuptools
Requires-Dist: cffi>=1.13
Requires-Dist: numpy>=1.20
Requires-Dist: black ; extra == "dev"
Requires-Dist: pre-commit ; extra == "dev"
Project-URL: Issues, https://github.com/yaq-project/yaqd-andor/issues
Project-URL: Source, https://github.com/yaq-project/yaqd-andor
Provides-Extra: dev
